geojsontools/__init__.py
geojsontools/geojsontools.py
geojsontools-0.0.3.dist-info/DESCRIPTION.rst
geojsontools-0.0.3.dist-info/METADATA
geojsontools-0.0.3.dist-info/RECORD
geojsontools-0.0.3.dist-info/WHEEL
geojsontools-0.0.3.dist-info/metadata.json
geojsontools-0.0.3.dist-info/top_level.txt
