Metadata-Version: 2.0
Name: geojsontools
Version: 0.0.3
Summary: Functions for manipulating geojsons
Home-page: https://github.com/platformstories/geojsontools
Author: Nikki Aldeborgh
Author-email: nikki.aldeborgh@digitalglobe.com
License: MIT
Platform: UNKNOWN
Requires-Dist: bumpversion
Requires-Dist: geojson (>=1.3.2)
Requires-Dist: numpy (>=1.12.0)
